alphaess/__init__.py
alphaess/alphaess.py
alphaess-0.0.18.dist-info/LICENSE
alphaess-0.0.18.dist-info/METADATA
alphaess-0.0.18.dist-info/WHEEL
alphaess-0.0.18.dist-info/top_level.txt
alphaess-0.0.18.dist-info/RECORD
