Metadata-Version: 2.1
Name: alphaess
Version: 0.0.18
Summary: A python library to retrieve energy statistics from your Alpha ESS inverter by polling the Alpha ESS web API.
Home-page: https://github.com/CharlesGillanders/alphaess
Author: Charles Gillanders
Author-email: charles@charlesgillanders.com
Classifier: Programming Language :: Python :: 3
Classifier: License :: OSI Approved :: MIT License
Classifier: Operating System :: OS Independent
License-File: LICENSE
